Metadata-Version: 2.1
Name: PETAnnotationDataset
Version: 0.0.1a3
Summary: PET annotation dataset
Home-page: http://www.example.com/it
Author: Patrizio Bellan
Author-email: patrizio.bellan@gmail.com
Maintainer: Patrizio Bellan
Maintainer-email: patrizio.bellan@gmail.com
License: MIT
Keywords: PET,dataset
Platform: Any
Classifier: Development Status :: 3 - Alpha
Classifier: License :: OSI Approved :: MIT License
Classifier: Natural Language :: English
Classifier: Intended Audience :: Science/Research
Classifier: Intended Audience :: Developers
Classifier: Intended Audience :: Education
Classifier: Intended Audience :: End Users/Desktop
Classifier: Intended Audience :: Information Technology
Classifier: Programming Language :: Python :: 3
Classifier: Programming Language :: Python :: 3.9
Classifier: Programming Language :: Python :: 3.10
Classifier: Programming Language :: Python :: 3.11
Classifier: Programming Language :: Python :: 3.12
Classifier: Topic :: Scientific/Engineering
Classifier: Topic :: Utilities
Requires-Python: !=2.7, >=3.7.*
